toloka_prefect/__init__.py
toloka_prefect/helpers.py
toloka_prefect/operations.py
toloka_prefect/utils.py
toloka_prefect-0.0.3.dist-info/AUTHORS
toloka_prefect-0.0.3.dist-info/LICENSE
toloka_prefect-0.0.3.dist-info/METADATA
toloka_prefect-0.0.3.dist-info/WHEEL
toloka_prefect-0.0.3.dist-info/top_level.txt
toloka_prefect-0.0.3.dist-info/RECORD
