Metadata-Version: 2.1
Name: toloka-prefect
Version: 0.0.3
Summary: Toloka prefect tasks library
Author: Vladislav Moiseev
Author-email: vlad-mois@yandex-team.ru
License: Apache 2.0
Project-URL: Source, https://github.com/Toloka/toloka-prefect
Platform: UNKNOWN
Classifier: Development Status :: 4 - Beta
Classifier: Intended Audience :: Developers
Classifier: Intended Audience :: Science/Research
Classifier: License :: OSI Approved :: Apache Software License
Classifier: Operating System :: OS Independent
Classifier: Programming Language :: Python
Classifier: Programming Language :: Python :: 3
Classifier: Programming Language :: Python :: 3.7
Classifier: Programming Language :: Python :: 3.8
Classifier: Programming Language :: Python :: 3.9
Classifier: Programming Language :: Python :: 3.10
Classifier: Programming Language :: Python :: Implementation :: CPython
Classifier: Topic :: Scientific/Engineering
Classifier: Topic :: Software Development
Classifier: Typing :: Typed
Requires-Python: >=3.7.0
License-File: LICENSE
License-File: AUTHORS
Requires-Dist: pandas (>=1.1.0)
Requires-Dist: prefect
Requires-Dist: requests
Requires-Dist: toloka-kit (==0.1.23)
